LICENSE
README.md
setup.py
src/MNHPy/Panel_Plot.py
src/MNHPy/__init__.py
src/MNHPy/misc_functions.py
src/MNHPy/read_MNHfile.py
src/MNHPy.egg-info/PKG-INFO
src/MNHPy.egg-info/SOURCES.txt
src/MNHPy.egg-info/dependency_links.txt
src/MNHPy.egg-info/requires.txt
src/MNHPy.egg-info/top_level.txt