Metadata-Version: 1.2
Name: MNHPy
Version: 0.3.1
Summary: Python visulization tools for MesoNH atmospheric research model
Home-page: https://github.com/QuentinRodier/MNHPy
Author: Quentin Rodier & Meso-NH Team
Author-email: mesonhsupport@obs-mip.fr
License: UNKNOWN
Platform: UNKNOWN
Classifier: Programming Language :: Python :: 3
Classifier: License :: CeCILL-C Free Software License Agreement (CECILL-C)
Requires-Python: >=3.8.10
